{
  "image": "train\\bonafide\\huawei\\indian-038_03.jpg",
  "template": "indian",
  "comments": [
    {
      "comment": "E1",
      "region_box": [
        1042,
        674,
        1680,
        860
      ],
      "lines": [
        {
          "text": "NAIR",
          "box": [
            1120,
            738,
            1334,
            797
          ]
        }
      ]
    },
    {
      "comment": "E2",
      "region_box": [
        1009,
        921,
        1961,
        1110
      ],
      "lines": [
        {
          "text": "LATA REKHA",
          "box": [
            1112,
            981,
            1633,
            1049
          ]
        }
      ]
    },
    {
      "comment": "E3",
      "region_box": [
        1036,
        1156,
        1751,
        1327
      ],
      "lines": [
        {
          "text": "24/12/1987",
          "box": [
            1110,
            1237,
            1616,
            1313
          ]
        }
      ]
    },
    {
      "comment": "E4",
      "region_box": [
        1017,
        1630,
        1722,
        1833
      ],
      "lines": [
        {
          "text": "का ताय Date c",
          "box": [
            1298,
            1630,
            1721,
            1666
          ]
        },
        {
          "text": "12/01/2007",
          "box": [
            1101,
            1708,
            1606,
            1785
          ]
        }
      ]
    },
    {
      "comment": "E5",
      "region_box": [
        2161,
        1656,
        2866,
        1848
      ],
      "lines": [
        {
          "text": "12/01/2017",
          "box": [
            2263,
            1725,
            2769,
            1796
          ]
        }
      ]
    }
  ]
}