{
  "image": "train\\bonafide\\huawei\\persian-NF-1043.jpg",
  "template": "persian",
  "comments": [
    {
      "comment": "E1",
      "region_box": [
        1107,
        382,
        1943,
        588
      ],
      "lines": [
        {
          "text": "Mina",
          "box": [
            1226,
            444,
            1429,
            511
          ]
        }
      ]
    },
    {
      "comment": "E2",
      "region_box": [
        1105,
        622,
        1932,
        834
      ],
      "lines": [
        {
          "text": "Ahmadi",
          "box": [
            1213,
            676,
            1550,
            741
          ]
        }
      ]
    },
    {
      "comment": "L1",
      "region_box": [
        2066,
        397,
        2748,
        560
      ],
      "lines": [
        {
          "text": "مینا",
          "box": [
            2168,
            454,
            2276,
            517
          ]
        }
      ]
    },
    {
      "comment": "L2",
      "region_box": [
        2050,
        636,
        2735,
        827
      ],
      "lines": [
        {
          "text": "محمدی",
          "box": [
            2163,
            698,
            2378,
            753
          ]
        }
      ]
    },
    {
      "comment": "E3",
      "region_box": [
        1121,
        882,
        1809,
        1067
      ],
      "lines": [
        {
          "text": "05/02/1994",
          "box": [
            1212,
            939,
            1664,
            1002
          ]
        }
      ]
    },
    {
      "comment": "E4",
      "region_box": [
        1123,
        1404,
        1775,
        1585
      ],
      "lines": [
        {
          "text": "08/07/2024",
          "box": [
            1199,
            1462,
            1647,
            1526
          ]
        }
      ]
    },
    {
      "comment": "E5",
      "region_box": [
        2085,
        1417,
        2719,
        1601
      ],
      "lines": [
        {
          "text": "13/10/2029",
          "box": [
            2147,
            1475,
            2597,
            1540
          ]
        }
      ]
    }
  ]
}