{
  "image": "train\\bonafide\\huawei\\persian-045_03.jpg",
  "template": "persian",
  "comments": [
    {
      "comment": "E1",
      "region_box": [
        1107,
        380,
        1944,
        585
      ],
      "lines": [
        {
          "text": "Farhad",
          "box": [
            1239,
            438,
            1534,
            502
          ]
        }
      ]
    },
    {
      "comment": "E2",
      "region_box": [
        1105,
        619,
        1933,
        830
      ],
      "lines": [
        {
          "text": "Kazemi",
          "box": [
            1234,
            670,
            1544,
            738
          ]
        }
      ]
    },
    {
      "comment": "L1",
      "region_box": [
        2067,
        395,
        2749,
        558
      ],
      "lines": [
        {
          "text": "فرهاد",
          "box": [
            2180,
            444,
            2342,
            518
          ]
        }
      ]
    },
    {
      "comment": "L2",
      "region_box": [
        2051,
        633,
        2736,
        824
      ],
      "lines": [
        {
          "text": "رحيمى",
          "box": [
            2172,
            708,
            2377,
            762
          ]
        }
      ]
    },
    {
      "comment": "E3",
      "region_box": [
        1121,
        878,
        1809,
        1063
      ],
      "lines": [
        {
          "text": "21/04/1990",
          "box": [
            1222,
            931,
            1676,
            999
          ]
        }
      ]
    },
    {
      "comment": "E4",
      "region_box": [
        1123,
        1397,
        1775,
        1578
      ],
      "lines": [
        {
          "text": "21/02/2024",
          "box": [
            1210,
            1454,
            1660,
            1519
          ]
        }
      ]
    },
    {
      "comment": "E5",
      "region_box": [
        2086,
        1410,
        2720,
        1594
      ],
      "lines": [
        {
          "text": "06/05/2029",
          "box": [
            2153,
            1468,
            2603,
            1534
          ]
        }
      ]
    }
  ]
}