{
  "image": "train\\bonafide\\scan\\chinese-102_03.jpg",
  "template": "chinese",
  "comments": [
    {
      "comment": "LE1",
      "region_box": [
        637,
        396,
        1104,
        582
      ],
      "lines": [
        {
          "text": "刘颖",
          "box": [
            685,
            437,
            781,
            483
          ]
        },
        {
          "text": "Liu Ying",
          "box": [
            678,
            492,
            884,
            541
          ]
        }
      ]
    },
    {
      "comment": "E2",
      "region_box": [
        1199,
        659,
        1609,
        793
      ],
      "lines": [
        {
          "text": "20 Nov 1989",
          "box": [
            1237,
            702,
            1560,
            744
          ]
        }
      ]
    },
    {
      "comment": "E3",
      "region_box": [
        1181,
        851,
        1633,
        978
      ],
      "lines": [
        {
          "text": "14 Jan 2015",
          "box": [
            1241,
            886,
            1552,
            929
          ]
        }
      ]
    },
    {
      "comment": "E4",
      "region_box": [
        617,
        1042,
        1088,
        1165
      ],
      "lines": [
        {
          "text": "11 Jan 2025",
          "box": [
            691,
            1084,
            999,
            1125
          ]
        }
      ]
    }
  ]
}