{
  "image": "train\\bonafide\\iphone15pro\\ukraine-NF-1057.jpg",
  "template": "ukraine",
  "comments": [
    {
      "comment": "LE1",
      "region_box": [
        803,
        335,
        1519,
        555
      ],
      "lines": [
        {
          "text": "Ткачук /",
          "box": [
            860,
            372,
            1137,
            434
          ]
        },
        {
          "text": "Tkachuk",
          "box": [
            860,
            446,
            1125,
            489
          ]
        }
      ]
    },
    {
      "comment": "LE2",
      "region_box": [
        767,
        582,
        1573,
        787
      ],
      "lines": [
        {
          "text": "Анна Василівна /",
          "box": [
            856,
            603,
            1417,
            671
          ]
        },
        {
          "text": "Anna",
          "box": [
            853,
            682,
            1011,
            723
          ]
        }
      ]
    },
    {
      "comment": "E3",
      "region_box": [
        778,
        841,
        1564,
        965
      ],
      "lines": [
        {
          "text": "06.04.1999",
          "box": [
            852,
            868,
            1208,
            917
          ]
        }
      ]
    },
    {
      "comment": "E4",
      "region_box": [
        782,
        1190,
        1537,
        1319
      ],
      "lines": [
        {
          "text": "07.09.2018",
          "box": [
            844,
            1225,
            1199,
            1276
          ]
        }
      ]
    },
    {
      "comment": "E5",
      "region_box": [
        774,
        1451,
        1551,
        1580
      ],
      "lines": [
        {
          "text": "06.09.2023",
          "box": [
            837,
            1481,
            1194,
            1531
          ]
        }
      ]
    }
  ]
}